MANIFEST.in
README.md
setup.py
yoloimport.py
yoloimport.egg-info/PKG-INFO
yoloimport.egg-info/SOURCES.txt
yoloimport.egg-info/dependency_links.txt
yoloimport.egg-info/top_level.txt