Metadata-Version: 1.1
Name: yoloimport
Version: 0.1.0
Summary: Never see another ImportError
Home-page: https://github.com/codysoyland/yoloimport
Author: Cody Soyland
Author-email: codysoyland@gmail.com
License: BSD
Platform: UNKNOWN
Classifier: Development Status :: 3 - Alpha
Classifier: License :: OSI Approved :: BSD License
